just_playlists.py
just_playlists-0.0.2.dist-info/LICENSE
just_playlists-0.0.2.dist-info/METADATA
just_playlists-0.0.2.dist-info/WHEEL
just_playlists-0.0.2.dist-info/top_level.txt
just_playlists-0.0.2.dist-info/RECORD
