Metadata-Version: 2.1
Name: just-playlists
Version: 0.0.2
Summary: A small playlists manager for just_playback
Author-email: KaneryU <kaneryu.yt@gmail.com>
Project-URL: Homepage, https://github.com/KaneryU/just_playlists/
Project-URL: Bug Tracker, https://github.com/KaneryU/just_playlists/issues
Classifier: Programming Language :: Python :: 3
Classifier: License :: OSI Approved :: MIT License
Classifier: Operating System :: OS Independent
Requires-Python: >=3.8
License-File: LICENSE
